Release/_swigwrapper.cp37-win_amd64.exp
Release/_swigwrapper.cp37-win_amd64.lib
Release/swigwrapper_wrap.obj
iara_stt_ctcdecoder/__init__.py
iara_stt_ctcdecoder/_swigwrapper.cp37-win_amd64.pyd
iara_stt_ctcdecoder/swigwrapper.py
iara_stt_ctcdecoder-1.6.2.dist-info/COPYING
iara_stt_ctcdecoder-1.6.2.dist-info/LICENSE.paddlepaddle
iara_stt_ctcdecoder-1.6.2.dist-info/LICENSE.parlance
iara_stt_ctcdecoder-1.6.2.dist-info/METADATA
iara_stt_ctcdecoder-1.6.2.dist-info/WHEEL
iara_stt_ctcdecoder-1.6.2.dist-info/top_level.txt
iara_stt_ctcdecoder-1.6.2.dist-info/RECORD
