Metadata-Version: 2.1
Name: iara-stt-ctcdecoder
Version: 1.6.2
Summary: Coqui STT Python decoder package.
Home-page: UNKNOWN
License: UNKNOWN
Platform: UNKNOWN
Requires-Dist: numpy
